latloncover/CDL_subcategories.csv
latloncover/LatLonConv.py
latloncover/__init__.py
latloncover/classify.py
latloncover/main.py
latloncover/tests/__init__.py
latloncover/tests/test_LatLonConv.py
latloncover/tests/test_classify.py
latloncover-0.1.0.dist-info/LICENSE
latloncover-0.1.0.dist-info/METADATA
latloncover-0.1.0.dist-info/WHEEL
latloncover-0.1.0.dist-info/entry_points.txt
latloncover-0.1.0.dist-info/top_level.txt
latloncover-0.1.0.dist-info/RECORD
