Metadata-Version: 2.1
Name: latloncover
Version: 0.1.0
Home-page: https://github.com/Imageomics/LatLonCover
Author: John Bradley
Author-email: john.bradley@duke.edu
License-File: LICENSE
Requires-Dist: requests ==2.31.0
Requires-Dist: click ==8.1.6
Requires-Dist: pandas ==2.0.3
Requires-Dist: geopandas ==0.13.2
